shauntal_tracker/__init__.py
shauntal_tracker/consistency_tracker.py
shauntal_tracker/test_consistency_tracker.py
shauntal_tracker-1.0.2.dist-info/METADATA
shauntal_tracker-1.0.2.dist-info/WHEEL
shauntal_tracker-1.0.2.dist-info/top_level.txt
shauntal_tracker-1.0.2.dist-info/RECORD
